passing_network_centrality/__init__.py
passing_network_centrality/transformations.py
passing_network_centrality-0.1.0.dist-info/LICENSE
passing_network_centrality-0.1.0.dist-info/WHEEL
passing_network_centrality-0.1.0.dist-info/METADATA
passing_network_centrality-0.1.0.dist-info/RECORD
