Metadata-Version: 2.1
Name: passing_network_centrality
Version: 0.1.0
Summary: A template Python module
Home-page: https://github.com/niesfutbol/passing_network_centrality
Author: NIES
Author-email: nepo@nies.futbol
Requires-Python: >=3.9
Classifier: License :: OSI Approved :: GNU General Public License v3 or later (GPLv3+)
Requires-Dist: numpy
